<nfeProc versao="4.00" xmlns="http://www.portalfiscal.inf.br/nfe"><NFe xmlns="http://www.portalfiscal.inf.br/nfe"><infNFe Id="NFe22260323439441005078550020015584671103248243" versao="4.00"><ide><cUF>22</cUF><cNF>10324824</cNF><natOp>VENDA DE MERCADORIA ADQUIRIDA OU RECEBIDA DE TERCEIROS</natOp><mod>55</mod><serie>2</serie><nNF>1558467</nNF><dhEmi>2026-03-18T11:35:42-03:00</dhEmi><dhSaiEnt>2026-03-18T11:35:42-03:00</dhSaiEnt><tpNF>1</tpNF><idDest>1</idDest><cMunFG>2200400</cMunFG><tpImp>1</tpImp><tpEmis>1</tpEmis><cDV>3</cDV><tpAmb>1</tpAmb><finNFe>1</finNFe><indFinal>0</indFinal><indPres>0</indPres><procEmi>0</procEmi><verProc>GMCore</verProc></ide><emit><CNPJ>23439441005078</CNPJ><xNome>ARMAZEM MATEUS S A CD ALTOS</xNome><enderEmit><xLgr>ROD BR 226 KM 03</xLgr><nro>SN</nro><xBairro>ZONA RURAL</xBairro><cMun>2200400</cMun><xMun>ALTOS</xMun><UF>PI</UF><CEP>64290000</CEP><cPais>1058</cPais><xPais>Brasil</xPais><fone>0021083500</fone></enderEmit><IE>197089585</IE><CRT>3</CRT></emit><dest><CNPJ>19525868000133</CNPJ><xNome>RODRIGO SOUZA SILVA</xNome><enderDest><xLgr>R PEDRO JOALHEIRO</xLgr><nro>468</nro><xBairro>AEROPORTO</xBairro><cMun>2211209</cMun><xMun>URUCUI</xMun><UF>PI</UF><CEP>64860000</CEP><cPais>1058</cPais><xPais>BRASIL</xPais><fone>089999404665</fone></enderDest><indIEDest>1</indIEDest><IE>195350260</IE></dest><det nItem="1"><prod><cProd>606492</cProd><cEAN>7898286191740</cEAN><xProd>CATCHUP MARATA PICANTE 370G</xProd><NCM>21032010</NCM><CFOP>5102</CFOP><uCom>UN</uCom><qCom>7</qCom><vUnCom>6.62</vUnCom><vProd>46.34</vProd><cEANTrib>7898286191740</cEANTrib><uTrib>UN</uTrib><qTrib>7</qTrib><vUnTrib>6.62</vUnTrib><indTot>1</indTot></prod><imposto><ICMS><ICMS20><orig>0</orig><CST>20</CST><modBC>2</modBC><pRedBC>46.6667</pRedBC><vBC>24.71</vBC><pICMS>22.50</pICMS><vICMS>5.56</vICMS></ICMS20></ICMS><PIS><PISOutr><CST>99</CST><vBC>0</vBC><pPIS>0</pPIS><vPIS>0</vPIS></PISOutr></PIS><COFINS><COFINSOutr><CST>99</CST><vBC>0</vBC><pCOFINS>0</pCOFINS><vCOFINS>0</vCOFINS></COFINSOutr></COFINS><IBSCBS><CST>000</CST><cClassTrib>000001</cClassTrib><gIBSCBS><vBC>40.78</vBC><gIBSUF><pIBSUF>0.1000</pIBSUF><vIBSUF>0.04</vIBSUF></gIBSUF><gIBSMun><pIBSMun>0.0000</pIBSMun><vIBSMun>0.00</vIBSMun></gIBSMun><vIBS>0.04</vIBS><gCBS><pCBS>0.9000</pCBS><vCBS>0.37</vCBS></gCBS></gIBSCBS></IBSCBS></imposto><vItem>46.34</vItem></det><det nItem="2"><prod><cProd>327381</cProd><cEAN>7898287990434</cEAN><xProd>COPO DESC MARATA TRANS 100X180ML</xProd><NCM>39241000</NCM><CFOP>5102</CFOP><uCom>UN</uCom><qCom>50</qCom><vUnCom>5.28</vUnCom><vProd>264</vProd><cEANTrib>7898287990434</cEANTrib><uTrib>UN</uTrib><qTrib>50</qTrib><vUnTrib>5.28</vUnTrib><indTot>1</indTot></prod><imposto><ICMS><ICMS20><orig>0</orig><CST>20</CST><modBC>2</modBC><pRedBC>46.6667</pRedBC><vBC>140.80</vBC><pICMS>22.50</pICMS><vICMS>31.68</vICMS></ICMS20></ICMS><PIS><PISAliq><CST>01</CST><vBC>232.32</vBC><pPIS>1.65</pPIS><vPIS>3.83</vPIS></PISAliq></PIS><COFINS><COFINSAliq><CST>01</CST><vBC>232.32</vBC><pCOFINS>7.60</pCOFINS><vCOFINS>17.66</vCOFINS></COFINSAliq></COFINS><IBSCBS><CST>000</CST><cClassTrib>000001</cClassTrib><gIBSCBS><vBC>210.83</vBC><gIBSUF><pIBSUF>0.1000</pIBSUF><vIBSUF>0.21</vIBSUF></gIBSUF><gIBSMun><pIBSMun>0.0000</pIBSMun><vIBSMun>0.00</vIBSMun></gIBSMun><vIBS>0.21</vIBS><gCBS><pCBS>0.9000</pCBS><vCBS>1.90</vCBS></gCBS></gIBSCBS></IBSCBS></imposto><vItem>264.00</vItem></det><det nItem="3"><prod><cProd>94843</cProd><cEAN>7898286190323</cEAN><xProd>MOLHO INGLES MARATA PET 150ML</xProd><NCM>21039021</NCM><CFOP>5102</CFOP><uCom>UN</uCom><qCom>24</qCom><vUnCom>3.34</vUnCom><vProd>80.16</vProd><cEANTrib>7898286190323</cEANTrib><uTrib>UN</uTrib><qTrib>24</qTrib><vUnTrib>3.34</vUnTrib><indTot>1</indTot></prod><imposto><ICMS><ICMS20><orig>0</orig><CST>20</CST><modBC>2</modBC><pRedBC>46.6667</pRedBC><vBC>42.75</vBC><pICMS>22.50</pICMS><vICMS>9.62</vICMS></ICMS20></ICMS><PIS><PISAliq><CST>01</CST><vBC>70.54</vBC><pPIS>1.65</pPIS><vPIS>1.16</vPIS></PISAliq></PIS><COFINS><COFINSAliq><CST>01</CST><vBC>70.54</vBC><pCOFINS>7.60</pCOFINS><vCOFINS>5.36</vCOFINS></COFINSAliq></COFINS><IBSCBS><CST>000</CST><cClassTrib>000001</cClassTrib><gIBSCBS><vBC>64.02</vBC><gIBSUF><pIBSUF>0.1000</pIBSUF><vIBSUF>0.06</vIBSUF></gIBSUF><gIBSMun><pIBSMun>0.0000</pIBSMun><vIBSMun>0.00</vIBSMun></gIBSMun><vIBS>0.06</vIBS><gCBS><pCBS>0.9000</pCBS><vCBS>0.58</vCBS></gCBS></gIBSCBS></IBSCBS></imposto><vItem>80.16</vItem></det><det nItem="4"><prod><cProd>56283</cProd><cEAN>7898286190316</cEAN><xProd>MOLHO PIMENTA MARATA GOTA 150ML</xProd><NCM>21039021</NCM><CFOP>5102</CFOP><uCom>UN</uCom><qCom>48</qCom><vUnCom>3.34</vUnCom><vProd>160.32</vProd><cEANTrib>7898286190316</cEANTrib><uTrib>UN</uTrib><qTrib>48</qTrib><vUnTrib>3.34</vUnTrib><indTot>1</indTot></prod><imposto><ICMS><ICMS20><orig>0</orig><CST>20</CST><modBC>2</modBC><pRedBC>46.6667</pRedBC><vBC>85.50</vBC><pICMS>22.50</pICMS><vICMS>19.24</vICMS></ICMS20></ICMS><PIS><PISAliq><CST>01</CST><vBC>141.08</vBC><pPIS>1.65</pPIS><vPIS>2.33</vPIS></PISAliq></PIS><COFINS><COFINSAliq><CST>01</CST><vBC>141.08</vBC><pCOFINS>7.60</pCOFINS><vCOFINS>10.72</vCOFINS></COFINSAliq></COFINS><IBSCBS><CST>000</CST><cClassTrib>000001</cClassTrib><gIBSCBS><vBC>128.03</vBC><gIBSUF><pIBSUF>0.1000</pIBSUF><vIBSUF>0.13</vIBSUF></gIBSUF><gIBSMun><pIBSMun>0.0000</pIBSMun><vIBSMun>0.00</vIBSMun></gIBSMun><vIBS>0.13</vIBS><gCBS><pCBS>0.9000</pCBS><vCBS>1.15</vCBS></gCBS></gIBSCBS></IBSCBS></imposto><vItem>160.32</vItem></det><det nItem="5"><prod><cProd>94844</cProd><cEAN>7898286190354</cEAN><xProd>MOLHO SHOYU GOTA PET 150ML</xProd><NCM>21039029</NCM><CFOP>5102</CFOP><uCom>UN</uCom><qCom>24</qCom><vUnCom>3.34</vUnCom><vProd>80.16</vProd><cEANTrib>7898286190354</cEANTrib><uTrib>UN</uTrib><qTrib>24</qTrib><vUnTrib>3.34</vUnTrib><indTot>1</indTot></prod><imposto><ICMS><ICMS20><orig>0</orig><CST>20</CST><modBC>2</modBC><pRedBC>46.6667</pRedBC><vBC>42.75</vBC><pICMS>22.50</pICMS><vICMS>9.62</vICMS></ICMS20></ICMS><PIS><PISAliq><CST>01</CST><vBC>70.54</vBC><pPIS>1.65</pPIS><vPIS>1.16</vPIS></PISAliq></PIS><COFINS><COFINSAliq><CST>01</CST><vBC>70.54</vBC><pCOFINS>7.60</pCOFINS><vCOFINS>5.36</vCOFINS></COFINSAliq></COFINS><IBSCBS><CST>000</CST><cClassTrib>000001</cClassTrib><gIBSCBS><vBC>64.02</vBC><gIBSUF><pIBSUF>0.1000</pIBSUF><vIBSUF>0.06</vIBSUF></gIBSUF><gIBSMun><pIBSMun>0.0000</pIBSMun><vIBSMun>0.00</vIBSMun></gIBSMun><vIBS>0.06</vIBS><gCBS><pCBS>0.9000</pCBS><vCBS>0.58</vCBS></gCBS></gIBSCBS></IBSCBS></imposto><vItem>80.16</vItem></det><det nItem="6"><prod><cProd>291606</cProd><cEAN>7898286190484</cEAN><xProd>VINAGRE ALCOOL GOTA PET 500ML</xProd><NCM>22090000</NCM><CFOP>5102</CFOP><uCom>UN</uCom><qCom>12</qCom><vUnCom>1.74</vUnCom><vProd>20.88</vProd><cEANTrib>7898286190484</cEANTrib><uTrib>UN</uTrib><qTrib>12</qTrib><vUnTrib>1.74</vUnTrib><indTot>1</indTot></prod><imposto><ICMS><ICMS20><orig>0</orig><CST>20</CST><modBC>2</modBC><pRedBC>46.6667</pRedBC><vBC>11.14</vBC><pICMS>22.50</pICMS><vICMS>2.51</vICMS></ICMS20></ICMS><PIS><PISAliq><CST>01</CST><vBC>18.37</vBC><pPIS>1.65</pPIS><vPIS>0.30</vPIS></PISAliq></PIS><COFINS><COFINSAliq><CST>01</CST><vBC>18.37</vBC><pCOFINS>7.60</pCOFINS><vCOFINS>1.40</vCOFINS></COFINSAliq></COFINS><IBSCBS><CST>000</CST><cClassTrib>000001</cClassTrib><gIBSCBS><vBC>16.67</vBC><gIBSUF><pIBSUF>0.1000</pIBSUF><vIBSUF>0.02</vIBSUF></gIBSUF><gIBSMun><pIBSMun>0.0000</pIBSMun><vIBSMun>0.00</vIBSMun></gIBSMun><vIBS>0.02</vIBS><gCBS><pCBS>0.9000</pCBS><vCBS>0.15</vCBS></gCBS></gIBSCBS></IBSCBS></imposto><vItem>20.88</vItem></det><total><ICMSTot><vBC>347.65</vBC><vICMS>78.23</vICMS><vICMSDeson>0</vICMSDeson><vFCPUFDest>0</vFCPUFDest><vICMSUFDest>0</vICMSUFDest><vICMSUFRemet>0</vICMSUFRemet><vFCP>0</vFCP><vBCST>0</vBCST><vST>0</vST><vFCPST>0</vFCPST><vFCPSTRet>0</vFCPSTRet><vProd>651.86</vProd><vFrete>0</vFrete><vSeg>0</vSeg><vDesc>0</vDesc><vII>0</vII><vIPI>0</vIPI><vIPIDevol>0</vIPIDevol><vPIS>8.78</vPIS><vCOFINS>40.50</vCOFINS><vOutro>0</vOutro><vNF>651.86</vNF></ICMSTot><IBSCBSTot><vBCIBSCBS>524.35</vBCIBSCBS><gIBS><gIBSUF><vDif>0.00</vDif><vDevTrib>0.00</vDevTrib><vIBSUF>0.52</vIBSUF></gIBSUF><gIBSMun><vDif>0.00</vDif><vDevTrib>0.00</vDevTrib><vIBSMun>0.00</vIBSMun></gIBSMun><vIBS>0.52</vIBS><vCredPres>0.00</vCredPres><vCredPresCondSus>0.00</vCredPresCondSus></gIBS><gCBS><vDif>0.00</vDif><vDevTrib>0.00</vDevTrib><vCBS>4.73</vCBS><vCredPres>0.00</vCredPres><vCredPresCondSus>0.00</vCredPresCondSus></gCBS></IBSCBSTot><vNFTot>651.86</vNFTot></total><transp><modFrete>0</modFrete><vol><qVol>165</qVol><esp>VOLUMES</esp><marca>DIVERSOS</marca><pesoL>36.550</pesoL><pesoB>36.550</pesoB></vol></transp><cobr><fat><nFat>1558467</nFat><vOrig>651.86</vOrig><vDesc>0</vDesc><vLiq>651.86</vLiq></fat><dup><nDup>001</nDup><dVenc>2026-04-09</dVenc><vDup>217.29</vDup></dup><dup><nDup>002</nDup><dVenc>2026-04-20</dVenc><vDup>217.29</vDup></dup><dup><nDup>003</nDup><dVenc>2026-04-29</dVenc><vDup>217.28</vDup></dup></cobr><pag><detPag><tPag>14</tPag><vPag>651.86</vPag></detPag></pag><infAdic><infCpl>Pedido: 1032482443 Cliente: 1188922 Pedido 9068879 CONHECIMENTO: 8139369. PLACA: PSN-7098 MOTORISTA: LEIREMARCOS LEITE DE OLIVEIRA. VENDEDOR: MIGUEL - URUCUI - PI.</infCpl></infAdic></infNFe><Signature xmlns="http://www.w3.org/2000/09/xmldsig#"><SignedInfo><CanonicalizationMethod Algorithm="http://www.w3.org/TR/2001/REC-xml-c14n-20010315" /><SignatureMethod Algorithm="http://www.w3.org/2000/09/xmldsig#rsa-sha1" /><Reference URI="#NFe22260323439441005078550020015584671103248243"><Transforms><Transform Algorithm="http://www.w3.org/2000/09/xmldsig#enveloped-signature" /><Transform Algorithm="http://www.w3.org/TR/2001/REC-xml-c14n-20010315" /></Transforms><DigestMethod Algorithm="http://www.w3.org/2000/09/xmldsig#sha1" /><DigestValue>BQSWd48pWZzose6R0aWgJbaLCNo=</DigestValue></Reference></SignedInfo><SignatureValue>VfcRGm5q+dcpPaDIor0Vsel/21KnN00n78Plc4f6X4TamsMzV8nl0MPI8vi16yTWd5NFCscnrBW/
QVzYI/S14I4F9HceqZhmkmJot6kbrviL5eT2itoh4iRWDiCGSEnlbnswV1ceU5P9YFX/lniHPXCH
5CuBdzT96bbKy8Eds1P6YzL9sLSixZ7VPal5KW3f2J4nQNeN/kgv+eM9dOi+auhaQMkIjiMh3moY
U9P04GyHjGY2IF6yKRnpVvA8i4zVrNZJaKquHBgQYZ+a1xVzAFOSFmCuJtsZi21O/HNZuQKNrKWz
8orSt/F91YUotO1NkehslOzEwuVjP5HyCTuSYQ==</SignatureValue><KeyInfo><X509Data><X509Certificate>MIIHPDCCBSSgAwIBAgIIWQwlERc//OwwDQYJKoZIhvcNAQELBQAwWTELMAkGA1UEBhMCQlIxEzAR
BgNVBAoTCklDUC1CcmFzaWwxFTATBgNVBAsTDEFDIFNPTFVUSSB2NTEeMBwGA1UEAxMVQUMgU09M
VVRJIE11bHRpcGxhIHY1MB4XDTI1MTExNzEzMjUwMFoXDTI2MTExNzEzMjUwMFowgeAxCzAJBgNV
BAYTAkJSMRMwEQYDVQQKEwpJQ1AtQnJhc2lsMQswCQYDVQQIEwJNQTERMA8GA1UEBxMIU2FvIEx1
aXMxHjAcBgNVBAsTFUFDIFNPTFVUSSBNdWx0aXBsYSB2NTEXMBUGA1UECxMOMzU2MjI0MDYwMDAx
OTAxHDAaBgNVBAsTE0NlcnRpZmljYWRvIERpZ2l0YWwxGjAYBgNVBAsTEUNlcnRpZmljYWRvIFBK
IEExMSkwJwYDVQQDEyBBUk1BWkVNIE1BVEVVUyBTQToyMzQzOTQ0MTAwMTMyMzCCASIwDQYJKoZI
hvcNAQEBBQADggEPADCCAQoCggEBAJXQKtzB0hHmibQbyBB7s0Xy8shQSx8xeEL5o/0XMa4p4cbC
SHdQPs95HGeCEyq0AVxmfdz8hHYntP5At13hI6zpZ0uPFPwIEDXevf/kqBMKoUzuvUmd9g9ToGfI
CcvOqHXvkhp/iu5EVOLx7lvnTmxWQlYh9ycwo190MsjpaY8K0dMVETa8NezS1TEJzue6k+M4Wk5q
299wPYPpSCNdv4PkiZyH1tVDWufLau21co3nJsS6A10qKfamEr3XijW/0edojN/YmC9nUMR1JxAg
pQWk0RkMUjZ6G91db2hHLnC9U+UXNhUlNOJP+n8fu74R5045MucXSIG0v0fsEoC3ogcCAwEAAaOC
An4wggJ6MAkGA1UdEwQCMAAwHwYDVR0jBBgwFoAUxVLtJYAJ35yCyJ9Hxt20XzHdubEwVAYIKwYB
BQUHAQEESDBGMEQGCCsGAQUFBzAChjhodHRwOi8vY2NkLmFjc29sdXRpLmNvbS5ici9sY3IvYWMt
c29sdXRpLW11bHRpcGxhLXY1LnA3YjCBuQYDVR0RBIGxMIGugRtjb250ZW5jaW9zb0BncnVwb21h
dGV1cy5jb22gIQYFYEwBAwKgGBMWSUxTT04gTUFURVVTIFJPRFJJR1VFU6AZBgVgTAEDA6AQEw4y
MzQzOTQ0MTAwMTMyM6A4BgVgTAEDBKAvEy0wNjAzMTk2MzIyNTg0MDEzMzA0MDAwMDAwMDAwMDAw
MDAwMDAwMDAwMDAwMDCgFwYFYEwBAwegDhMMMDAwMDAwMDAwMDAwMF0GA1UdIARWMFQwUgYGYEwB
AgEmMEgwRgYIKwYBBQUHAgEWOmh0dHA6Ly9jY2QuYWNzb2x1dGkuY29tLmJyL2RvY3MvZHBjLWFj
LXNvbHV0aS1tdWx0aXBsYS5wZGYwHQYDVR0lBBYwFAYIKwYBBQUHAwIGCCsGAQUFBwMEMIGMBgNV
HR8EgYQwgYEwPqA8oDqGOGh0dHA6Ly9jY2QuYWNzb2x1dGkuY29tLmJyL2xjci9hYy1zb2x1dGkt
bXVsdGlwbGEtdjUuY3JsMD+gPaA7hjlodHRwOi8vY2NkMi5hY3NvbHV0aS5jb20uYnIvbGNyL2Fj
LXNvbHV0aS1tdWx0aXBsYS12NS5jcmwwHQYDVR0OBBYEFMnX2EwnD0O9YzdiSGEjgRlbogOUMA4G
A1UdDwEB/wQEAwIF4DANBgkqhkiG9w0BAQsFAAOCAgEAayjU6c3q5VPAfd+Y+4kU1s2Pi11HqXhL
MI41ZeXcTsWw+fGZavIbxmPzwyqzGMo3AUeHgGxUX/kKXpqmd1MBnAJmQK0B1CUAD9bMx0r7lmKe
7kkPRgs0f477HXqFjFcNbZrdCwllGuu6QUDBUcQ3EXkemOMKGaTJxQwVVAF2Dyy6xgDZ42qVPOtO
8XXIHbkrBtFTdcMoHQpLtX/NFKKa9jIXhU6tnoajQofjjsLBatUCe6fd5GGshGvZRjqZfzBX55cz
JahpdvHtL78cv7qWlYoE9a/asUbBOEnUIarFINN8bp9CXFh6tgNtvotdk1Ydplyew5Oxu/YeJ+uL
irhi28g1nTdwY3m6i8ET1d/rldzcOGaqqVMeVC/Rm4tRqotVGNuaUrwvrpOfk3UWm3QEKqpP0K14
lkLZFQENWr2D8nUhKI/m7nT0oUTGJ/M/SN9H6T6TveCup/+tdVuH/u2n9Kxg0gtXWPpE7gX6fJxx
dbjG5BCW5pOVxyJ1lm/fnpP+Y6l7hVD6mPjAtH9CsUZu1lyzpRjtvaRu31RElyZxSDWcSjblxPz2
91LfL6RaOCHfoSH5zEBRz9CZKlK2ST3rt/cJx8qkFLzUuiBCfc2UnXjOqMwCt0HrS4Fkf1kR+vNv
+v9DmVov0OkyZNIS0/yIkBb9hgddXih/XZW9/1BFuy8=</X509Certificate></X509Data></KeyInfo></Signature></NFe><protNFe versao="4.00" xmlns="http://www.portalfiscal.inf.br/nfe"><infProt><tpAmb>1</tpAmb><verAplic>SVRS2601161142DR</verAplic><chNFe>22260323439441005078550020015584671103248243</chNFe><dhRecbto>2026-03-18T11:35:44-03:00</dhRecbto><nProt>222260006424081</nProt><digVal>BQSWd48pWZzose6R0aWgJbaLCNo=</digVal><cStat>100</cStat><xMotivo>Autorizado o uso da NF-e</xMotivo></infProt></protNFe></nfeProc>